array_cache/__init__.py
array_cache-1.0.1.dist-info/LICENSE
array_cache-1.0.1.dist-info/METADATA
array_cache-1.0.1.dist-info/WHEEL
array_cache-1.0.1.dist-info/top_level.txt
array_cache-1.0.1.dist-info/RECORD
