Metadata-Version: 2.1
Name: array-cache
Version: 1.0.1
Summary: Cache the current index of you array
Author-email: n4n5 <its.just.n4n5@gmail.com>
License: MIT License
Project-URL: Homepage, https://github.com/Its-Just-Nans/array-cache
Project-URL: Bug Tracker, https://github.com/Its-Just-Nans/array-cache/issues
Keywords: cache,array,array-cache,array_cache,arraycache
Classifier: License :: OSI Approved :: MIT License
Classifier: Programming Language :: Python
Classifier: Programming Language :: Python :: 3
Requires-Python: >=3.6
License-File: LICENSE
